{
    "key": "group_65b0d0efacfcc",
    "title": "Sub Menus",
    "fields": [
        {
            "key": "field_65b0d0f04cc93",
            "label": "Left Submenus",
            "name": "left_submenus",
            "aria-label": "",
            "type": "repeater",
            "instructions": "",
            "required": 0,
            "conditional_logic": 0,
            "wrapper": {
                "width": "",
                "class": "",
                "id": ""
            },
            "layout": "row",
            "pagination": 0,
            "min": 0,
            "max": 0,
            "collapsed": "",
            "button_label": "Add Row",
            "rows_per_page": 20,
            "sub_fields": [
                {
                    "key": "field_65b0d1bf4cc95",
                    "label": "Group Name",
                    "name": "group_name",
                    "aria-label": "",
                    "type": "text",
                    "instructions": "",
                    "required": 0,
                    "conditional_logic": 0,
                    "wrapper": {
                        "width": "",
                        "class": "",
                        "id": ""
                    },
                    "default_value": "",
                    "maxlength": "",
                    "placeholder": "",
                    "prepend": "",
                    "append": "",
                    "parent_repeater": "field_65b0d0f04cc93"
                },
                {
                    "key": "field_65b0d1dd4cc96",
                    "label": "Group Links",
                    "name": "group_links",
                    "aria-label": "",
                    "type": "repeater",
                    "instructions": "",
                    "required": 0,
                    "conditional_logic": 0,
                    "wrapper": {
                        "width": "",
                        "class": "",
                        "id": ""
                    },
                    "layout": "row",
                    "pagination": 0,
                    "min": 0,
                    "max": 0,
                    "collapsed": "",
                    "button_label": "Add Row",
                    "rows_per_page": 20,
                    "sub_fields": [
                        {
                            "key": "field_65b0d1f04cc97",
                            "label": "Link",
                            "name": "link",
                            "aria-label": "",
                            "type": "link",
                            "instructions": "",
                            "required": 0,
                            "conditional_logic": 0,
                            "wrapper": {
                                "width": "",
                                "class": "",
                                "id": ""
                            },
                            "return_format": "array",
                            "parent_repeater": "field_65b0d1dd4cc96"
                        },
                        {
                            "key": "field_65b0d75addfed",
                            "label": "Link Subtitle",
                            "name": "link_subtitle",
                            "aria-label": "",
                            "type": "text",
                            "instructions": "",
                            "required": 0,
                            "conditional_logic": 0,
                            "wrapper": {
                                "width": "",
                                "class": "",
                                "id": ""
                            },
                            "default_value": "",
                            "maxlength": "",
                            "placeholder": "",
                            "prepend": "",
                            "append": "",
                            "parent_repeater": "field_65b0d1dd4cc96"
                        }
                    ],
                    "parent_repeater": "field_65b0d0f04cc93"
                }
            ]
        },
        {
            "key": "field_65b0d4fbc9836",
            "label": "Right Submenus",
            "name": "right_submenus",
            "aria-label": "",
            "type": "repeater",
            "instructions": "",
            "required": 0,
            "conditional_logic": 0,
            "wrapper": {
                "width": "",
                "class": "",
                "id": ""
            },
            "layout": "row",
            "pagination": 0,
            "min": 0,
            "max": 0,
            "collapsed": "",
            "button_label": "Add Row",
            "rows_per_page": 20,
            "sub_fields": [
                {
                    "key": "field_65b0d4fbc9838",
                    "label": "Group Name",
                    "name": "group_name",
                    "aria-label": "",
                    "type": "text",
                    "instructions": "",
                    "required": 0,
                    "conditional_logic": 0,
                    "wrapper": {
                        "width": "",
                        "class": "",
                        "id": ""
                    },
                    "default_value": "",
                    "maxlength": "",
                    "placeholder": "",
                    "prepend": "",
                    "append": "",
                    "parent_repeater": "field_65b0d4fbc9836"
                },
                {
                    "key": "field_65b0d4fbc9839",
                    "label": "Group Links",
                    "name": "group_links",
                    "aria-label": "",
                    "type": "repeater",
                    "instructions": "",
                    "required": 0,
                    "conditional_logic": 0,
                    "wrapper": {
                        "width": "",
                        "class": "",
                        "id": ""
                    },
                    "layout": "row",
                    "min": 0,
                    "max": 0,
                    "collapsed": "",
                    "button_label": "Add Row",
                    "rows_per_page": 20,
                    "sub_fields": [
                        {
                            "key": "field_65b0d4fbc983a",
                            "label": "Link",
                            "name": "link",
                            "aria-label": "",
                            "type": "link",
                            "instructions": "",
                            "required": 0,
                            "conditional_logic": 0,
                            "wrapper": {
                                "width": "",
                                "class": "",
                                "id": ""
                            },
                            "return_format": "array",
                            "parent_repeater": "field_65b0d4fbc9839"
                        },
                        {
                            "key": "field_65b0d79a67c3c",
                            "label": "Link Subtitle",
                            "name": "link_subtitle",
                            "aria-label": "",
                            "type": "text",
                            "instructions": "",
                            "required": 0,
                            "conditional_logic": 0,
                            "wrapper": {
                                "width": "",
                                "class": "",
                                "id": ""
                            },
                            "default_value": "",
                            "maxlength": "",
                            "placeholder": "",
                            "prepend": "",
                            "append": "",
                            "parent_repeater": "field_65b0d4fbc9839"
                        }
                    ],
                    "parent_repeater": "field_65b0d4fbc9836"
                }
            ]
        },
        {
            "key": "field_65b0d52bc983b",
            "label": "Right Content",
            "name": "right_content",
            "aria-label": "",
            "type": "group",
            "instructions": "",
            "required": 0,
            "conditional_logic": 0,
            "wrapper": {
                "width": "",
                "class": "",
                "id": ""
            },
            "layout": "row",
            "sub_fields": [
                {
                    "key": "field_65b0dda546ccb",
                    "label": "Custom HTML",
                    "name": "custom_html",
                    "aria-label": "",
                    "type": "wysiwyg",
                    "instructions": "",
                    "required": 0,
                    "conditional_logic": 0,
                    "wrapper": {
                        "width": "",
                        "class": "",
                        "id": ""
                    },
                    "default_value": "",
                    "tabs": "all",
                    "toolbar": "full",
                    "media_upload": 1,
                    "delay": 0
                }
            ]
        }
    ],
    "location": [
        [
            {
                "param": "post_type",
                "operator": "==",
                "value": "nav"
            }
        ]
    ],
    "menu_order": 0,
    "position": "acf_after_title",
    "style": "default",
    "label_placement": "top",
    "instruction_placement": "label",
    "hide_on_screen": "",
    "active": true,
    "description": "",
    "show_in_rest": 0,
    "modified": 1706183087
}
